lawnmower/__init__.py
lawnmower/__main__.py
lawnmower-0.0.1b0.dist-info/entry_points.txt
lawnmower-0.0.1b0.dist-info/WHEEL
lawnmower-0.0.1b0.dist-info/METADATA
lawnmower-0.0.1b0.dist-info/RECORD
