Metadata-Version: 2.1
Name: lawnmower
Version: 0.0.1b0
Summary: LAWNMOWER - Simple Python task runner
License: GPL-3.0-only
Keywords: build system,make,mow,task runner,scripts
Author: arnu515
Author-email: arnu515@protonmail.com
Requires-Python: >=3.6,<4.0
Classifier: Development Status :: 4 - Beta
Classifier: Environment :: Console
Classifier: Intended Audience :: Developers
Classifier: License :: OSI Approved :: GNU General Public License v3 (GPLv3)
Classifier: License :: Other/Proprietary License
Classifier: Natural Language :: English
Classifier: Programming Language :: Python :: 3
Classifier: Programming Language :: Python :: 3.6
Classifier: Programming Language :: Python :: 3.7
Classifier: Programming Language :: Python :: 3.8
Classifier: Programming Language :: Python :: 3.9
Classifier: Topic :: Software Development
Classifier: Typing :: Typed
